{
  "channel_name": "KuchenTV",
  "subscriber_count": "1.19 Mio.",
  "video_count": "1799",
  "description": "Impressum",
  "links": {
    "instagram": "https://www.instagram.com/kuchentv/",
    "twitch": "https://www.twitch.tv/KuchenTV",
    "website": "https://needitnow.de/",
    "discord": "https://www.discord.gg/kuchentv",
    "steam": "https://steamcommunity.com/groups/Kuchenrepublik"
  },
  "other_channels": {
    "Tim Heldt": "https://www.youtube.com/c/TimundTimothy",
    "iKuchen": "https://www.youtube.com/ikuchen",
    "Gameplay": "https://www.youtube.com/KuuchenGeschmack",
    "KuchenTV Uncut": "https://www.youtube.com/LeIKuchenblogx"
  },
  "impressum": "Tim Heldt Filmherstellung c/o Werneburg Internet Marketing und Publikations-Service Philipp-Kühner-Straße 2 99817 Eisenach ACHTUNG! Adresse ist NICHT für Fanpost"
}
